main_integrated.py
ui_components.py
screens/__init__.py
screens/database.py
screens/first_access.py
screens/help.py
screens/jobs.py
screens/logs.py
screens/photos.py
screens/reports.py
screens/settings.py
screens/splash.py
screens/tokens.py
src/__init__.py
src/__main__.py
src/__main_console__.py
src/gui_main.py
src/imports.py
src/interface_grafica.py
src/layout.py
src/log_types.py
src/token_manager.py
src/utils.py
src/api/__init__.py
src/api/api_mplace.py
src/api/oking.py
src/api/okinghub.py
src/api/okvendas.py
src/api/slack.py
src/api/entities/__init__.py
src/api/entities/client_erp_code.py
src/api/entities/cliente.py
src/api/entities/cliente_aprovado.py
src/api/entities/comissao.py
src/api/entities/contas_a_receber.py
src/api/entities/encaminha.py
src/api/entities/entregue.py
src/api/entities/estoque.py
src/api/entities/estoque_mplace.py
src/api/entities/estoque_okvendas.py
src/api/entities/foto.py
src/api/entities/foto_sku.py
src/api/entities/imposto_produto.py
src/api/entities/pedido.py
src/api/entities/plano_pagamento_cliente.py
src/api/entities/preco.py
src/api/entities/preco_lista.py
src/api/entities/preco_mplace.py
src/api/entities/preco_okvendas.py
src/api/entities/produto.py
src/api/entities/produto_mplace.py
src/api/entities/produto_okvendas.py
src/api/entities/produto_parceiro_mplace.py
src/api/entities/representante.py
src/api/entities/service_fee.py
src/api/entities/transportadora_fob_parceiro.py
src/database/__init__.py
src/database/connection.py
src/database/queries.py
src/database/utils.py
src/database/entities/__init__.py
src/database/entities/client.py
src/database/entities/client_payment_plan.py
src/database/entities/price_list.py
src/database/entities/product_tax.py
src/database/entities/representative.py
src/database/oracle2/instantclient_21_6/BASIC_LICENSE
src/database/oracle2/instantclient_21_6/BASIC_README
src/database/oracle2/instantclient_21_6/adrci.exe
src/database/oracle2/instantclient_21_6/adrci.sym
oking-4.6.27.dist-info/LICENSE
oking-4.6.27.dist-info/METADATA
oking-4.6.27.dist-info/WHEEL
oking-4.6.27.dist-info/entry_points.txt
oking-4.6.27.dist-info/top_level.txt
oking-4.6.27.dist-info/RECORD
