Metadata-Version: 2.1
Name: oking
Version: 4.6.27
Summary: Pacote de integração de produtos, preço, estoque e pedidos com o sistema OkVendas da Openk
Home-page: UNKNOWN
Author: Openk Tecnologia
Author-email: <suporte.b2c@openk.com.br>
License: UNKNOWN
Keywords: python,oking,openk,okvendas,ok
Platform: UNKNOWN
Classifier: Development Status :: 4 - Beta
Classifier: Intended Audience :: Developers
Classifier: Programming Language :: Python :: 3
Classifier: Operating System :: Unix
Classifier: Operating System :: Microsoft :: Windows
License-File: LICENSE
Requires-Dist: schedule
Requires-Dist: requests
Requires-Dist: configparser
Requires-Dist: logger
Requires-Dist: jsonpickle
Requires-Dist: PySimpleGUI
Requires-Dist: pandas
Requires-Dist: pynput
Requires-Dist: setuptools
Requires-Dist: cryptography
Requires-Dist: psutil
Provides-Extra: photo
Requires-Dist: Pillow (>=10.0.0) ; extra == 'photo'
